mappings_utility/__init__.py
mappings_utility/mapping_svc.py
mappings_utility/mapping_utility.py
mappings_utility/sdmx_mapping_utility.py
mappings_utility/sdmx_structures.py
mappings_utility-0.2.6.dist-info/METADATA
mappings_utility-0.2.6.dist-info/WHEEL
mappings_utility-0.2.6.dist-info/RECORD
