Metadata-Version: 2.1
Name: mappings_utility
Version: 0.2.6
Summary: mapping utility tool for sdmx based partial mappings
Author: Gyorgy Gyomai
Author-email: gyorgy.gyomai@oecd.org
Requires-Python: >=3.12,<4.0
Classifier: Programming Language :: Python :: 3
Classifier: Programming Language :: Python :: 3.12
Classifier: Programming Language :: Python :: 3.13
Requires-Dist: fastapi (>=0.115.0,<0.116.0)
Requires-Dist: pandas (>=2.2.0,<3.0.0)
Requires-Dist: pydantic (>=2.9.0,<3.0.0)
Requires-Dist: requests (>=2.32.0,<3.0.0)
Requires-Dist: uvicorn (>=0.32.0,<0.33.0)
